krules_companion_client/__init__.py
krules_companion_client/commands.py
krules_companion_client/models.py
krules_companion_client/accounts/__init__.py
krules_companion_client/google/__init__.py
krules_companion_client/http/__init__.py
krules_companion_client-2.0.0.dist-info/METADATA
krules_companion_client-2.0.0.dist-info/WHEEL
krules_companion_client-2.0.0.dist-info/entry_points.txt
krules_companion_client-2.0.0.dist-info/RECORD
